decoder_ring/__init__.py
decoder_ring/basic-demo.py
decoder_ring/decoders.py
decoder_ring-0.1.2.dist-info/LICENSE
decoder_ring-0.1.2.dist-info/METADATA
decoder_ring-0.1.2.dist-info/WHEEL
decoder_ring-0.1.2.dist-info/top_level.txt
decoder_ring-0.1.2.dist-info/RECORD
