Metadata-Version: 2.1
Name: decoder-ring
Version: 0.1.2
Summary: Type-hinted interface to use several decoders on text-generation models
Author-email: Nick Doiron <ndoiron@mapmeld.com>
License: Copyright 2022- Nick Doiron. All rights reserved.
Project-URL: Homepage, https://github.com/georeactor/decoder_ring
Keywords: transformers,decoder,text generation
Requires-Python: >=3.9
License-File: LICENSE
Provides-Extra: dev
Requires-Dist: black ; extra == 'dev'
Requires-Dist: pylint ; extra == 'dev'
Requires-Dist: mypy ; extra == 'dev'
